extrainterpreters/lock.py
extrainterpreters/remote_array.py
extrainterpreters/utils.py
extrainterpreters/memoryboard.py
extrainterpreters/queue.py
extrainterpreters/piped_interpreter.py
extrainterpreters/memoryboard.c
extrainterpreters/resources.py
extrainterpreters/simple_interpreter.py
extrainterpreters/base_interpreter.py
extrainterpreters/__init__.py
extrainterpreters/_memoryboard.cpython-312-x86_64-linux-musl.so
extrainterpreters-0.3.0.dist-info/WHEEL
extrainterpreters-0.3.0.dist-info/top_level.txt
extrainterpreters-0.3.0.dist-info/METADATA
extrainterpreters-0.3.0.dist-info/RECORD
extrainterpreters-0.3.0.dist-info/licenses/LICENSE
