Metadata-Version: 2.4
Name: extrainterpreters
Version: 0.3.0
Summary: PEP 554 Subinterpreters usable from Python code
Author: Joao S. O. Bueno
Project-URL: repository, https://github.com/jsbueno/extrainterpreters
Classifier: Development Status :: 4 - Beta
Classifier: Intended Audience :: Developers
Classifier: Programming Language :: Python :: 3.12
Classifier: Programming Language :: Python :: 3.13
Classifier: Programming Language :: Python :: 3.14
Classifier: Programming Language :: Python :: Implementation :: CPython
Classifier: License :: OSI Approved :: GNU Lesser General Public License v3 or later (LGPLv3+)
Classifier: Operating System :: OS Independent
Requires-Python: >=3.12
License-File: LICENSE
Provides-Extra: dev
Requires-Dist: pytest; extra == "dev"
Requires-Dist: black; extra == "dev"
Requires-Dist: pyflakes; extra == "dev"
Requires-Dist: pytest-coverage; extra == "dev"
Dynamic: license-file
